epex_sftp/__init__.py
epex_sftp/env_vars.py
epex_sftp/epex_sftp_plugin.py
meteomatics_api/__init__.py
meteomatics_api/env_vars.py
meteomatics_api/forecast_postcode_disticts.dat
meteomatics_api/meteomatics_api_plugin.py
meteomatics_api/postcode_districts.dat
batch_plugins-1.0.22.dist-info/METADATA
batch_plugins-1.0.22.dist-info/WHEEL
batch_plugins-1.0.22.dist-info/top_level.txt
batch_plugins-1.0.22.dist-info/RECORD
