Metadata-Version: 2.4
Name: batch_plugins
Version: 1.0.22
Summary: batchs plugins
Author-email: DataGlue <data-team@cfp.energy>
License: BSD-3-Clause
Keywords: batchs,plugins
Classifier: Programming Language :: Python :: 3
Requires-Python: >=3.9
Requires-Dist: boto3==1.24.16
Requires-Dist: botocore==1.27.16
Requires-Dist: numpy==1.26.4
Requires-Dist: pandas==2.1.1
Requires-Dist: paramiko==2.11.0
Requires-Dist: requests==2.28.1
Requires-Dist: SQLAlchemy==1.4.39
Requires-Dist: oauthlib==3.2.2
Requires-Dist: requests_oauthlib==1.3.1
Requires-Dist: lxml==5.3.0
Requires-Dist: html5lib==1.1
Requires-Dist: meteomatics==2.9.0
Requires-Dist: cssselect==1.2.0
Requires-Dist: openpyxl==3.1.2
Requires-Dist: tzdata==2024.1
Requires-Dist: importlib-metadata; python_version < "3.10"
Provides-Extra: pdf
Requires-Dist: ReportLab>=1.2; extra == "pdf"
Requires-Dist: RXP; extra == "pdf"
Provides-Extra: rest
Requires-Dist: docutils>=0.3; extra == "rest"
Requires-Dist: pack==1.1,==1.3; extra == "rest"
